README.rst
setup.py
pyad_auth/__init__.py
pyad_auth/pyad_auth.py
pyad_auth.egg-info/PKG-INFO
pyad_auth.egg-info/SOURCES.txt
pyad_auth.egg-info/dependency_links.txt
pyad_auth.egg-info/pbr.json
pyad_auth.egg-info/requires.txt
pyad_auth.egg-info/top_level.txt