Metadata-Version: 1.1
Name: pyad-auth
Version: 0.0.2
Summary: A simple Active Directory user authorization tool.
Home-page: https://github.com/jmensch/pyad_auth/
Author: James Mensch
Author-email: james@jamesmensch.com
License: MIT
Download-URL: https://github.com/jmensch/pyad_auth/
Keywords: python microsoft windows active directory AD adsi
Platform: UNKNOWN
Classifier: Development Status :: 4 - Beta
Classifier: License :: OSI Approved :: MIT License
Classifier: Intended Audience :: System Administrators
Classifier: Natural Language :: English
Classifier: Operating System :: OS Independent
Classifier: Topic :: System :: Systems Administration :: Authentication/Directory :: LDAP
